pyfastcore/__init__.py
pyfastcore/fastcore.py
pyfastcore/utils.py
pyfastcore-0.0.6.dist-info/LICENSE
pyfastcore-0.0.6.dist-info/METADATA
pyfastcore-0.0.6.dist-info/WHEEL
pyfastcore-0.0.6.dist-info/top_level.txt
pyfastcore-0.0.6.dist-info/RECORD
