Metadata-Version: 2.1
Name: pyfastcore
Version: 0.0.6
Summary: A python-based implementation for the context-specific metabolic model extraction methods from Vlassis et al. 2014
Home-page: https://github.com/migp11/pyfastcore
Author: Miguel Ponce-de-Leon
Author-email: miguelponcedeleon@gmail.com
Maintainer: Miguel Ponce-de-Leon
Maintainer-email: miguelponcedeleon@gmail.com
License: UNKNOWN
Platform: UNKNOWN
Classifier: Programming Language :: Python :: 3
Classifier: License :: OSI Approved :: MIT License
Classifier: Operating System :: OS Independent
Requires-Python: >=3.6
License-File: LICENSE
Requires-Dist: numpy
Requires-Dist: cobra (>=0.25.0)
